systemfixtures/__init__.py
systemfixtures/_overlay.py
systemfixtures/executable.py
systemfixtures/filesystem.py
systemfixtures/groups.py
systemfixtures/matchers.py
systemfixtures/network.py
systemfixtures/threads.py
systemfixtures/time.py
systemfixtures/users.py
systemfixtures/processes/__init__.py
systemfixtures/processes/dpkg.py
systemfixtures/processes/fixture.py
systemfixtures/processes/systemctl.py
systemfixtures/processes/wget.py
systemfixtures/processes/tests/__init__.py
systemfixtures/processes/tests/test_dpkg.py
systemfixtures/processes/tests/test_fixture.py
systemfixtures/processes/tests/test_systemctl.py
systemfixtures/processes/tests/test_wget.py
systemfixtures/tests/__init__.py
systemfixtures/tests/test_executable.py
systemfixtures/tests/test_filesystem.py
systemfixtures/tests/test_groups.py
systemfixtures/tests/test_network.py
systemfixtures/tests/test_threads.py
systemfixtures/tests/test_time.py
systemfixtures/tests/test_users.py
systemfixtures-0.6.5.dist-info/DESCRIPTION.rst
systemfixtures-0.6.5.dist-info/METADATA
systemfixtures-0.6.5.dist-info/RECORD
systemfixtures-0.6.5.dist-info/WHEEL
systemfixtures-0.6.5.dist-info/metadata.json
systemfixtures-0.6.5.dist-info/pbr.json
systemfixtures-0.6.5.dist-info/top_level.txt
