Metadata-Version: 2.0
Name: systemfixtures
Version: 0.6.5
Summary: Test fixtures for providing fake versions of various system resources (processes, users, groups, etc.)
Home-page: https://github.com/testing-cabal/systemfixtures
Author: Free Ekanayaka
Author-email: free@ekanayaka.io
License: MIT
Platform: POSIX
Classifier: License :: OSI Approved :: MIT License
Classifier: Operating System :: POSIX
Classifier: Programming Language :: Python :: 3
Requires-Dist: fakesleep
Requires-Dist: fixtures
Requires-Dist: pbr
Requires-Dist: requests-mock
Requires-Dist: six
Requires-Dist: testtools
Requires-Dist: subprocess32; (python_version < '3.5')
Provides-Extra: test
Requires-Dist: coverage (>=4.2); extra == 'test'
Requires-Dist: sphinx; extra == 'test'
